cerebral/GFA.py
cerebral/__init__.py
cerebral/_version.py
cerebral/features.py
cerebral/kfolds.py
cerebral/layers.py
cerebral/loss.py
cerebral/metrics.py
cerebral/models.py
cerebral/novelty.py
cerebral/permutation.py
cerebral/plots.py
cerebral/py.typed
cerebral/tuning.py
cerebral-0.0.8.dist-info/LICENSE
cerebral-0.0.8.dist-info/METADATA
cerebral-0.0.8.dist-info/WHEEL
cerebral-0.0.8.dist-info/top_level.txt
cerebral-0.0.8.dist-info/RECORD
